<?xml version="1.0"?>
<opencv_storage>
<stage0>
  <maxWeakCount>2</maxWeakCount>
  <stageThreshold>-2.3790319263935089e-01</stageThreshold>
  <weakClassifiers>
    <_>
      <internalNodes>
        1 2 318179 -3.1935773789882660e-02 0 -1 443697
        -1.2866383418440819e-02 -2 -3 43110 1.5957418084144592e-01</internalNodes>
      <leafValues>
        -1. 9.6230596303939819e-01 -9.1872793436050415e-01
        6.4285713434219360e-01</leafValues></_>
    <_>
      <internalNodes>
        1 2 74147 1.5988092124462128e-01 0 -1 490420
        6.8277651444077492e-03 -2 -3 71523 -2.4642802774906158e-02</internalNodes>
      <leafValues>
        -8.8076031208038330e-01 6.8137133121490479e-01
        -8.7192988395690918e-01 9.6440768241882324e-01</leafValues></_></weakClassifiers></stage0>
</opencv_storage>
